eonr/__init__.py
eonr/eonr.py
eonr/models.py
eonr/plotting_tools.py
eonr/data/minnesota_2012.csv
eonr/examples/advanced_tutorial.ipynb
eonr/examples/advanced_tutorial.py
eonr/examples/tutorial.ipynb
eonr/examples/tutorial.py
eonr/examples/data/minnesota_2012.csv
eonr/tests/test.py
eonr/tests/test_eonr.py
eonr/tests/test_models.py
eonr/tests/test_settings.py
eonr-0.2.1.dist-info/LICENSE
eonr-0.2.1.dist-info/METADATA
eonr-0.2.1.dist-info/WHEEL
eonr-0.2.1.dist-info/top_level.txt
eonr-0.2.1.dist-info/RECORD
