Metadata-Version: 2.1
Name: eonr
Version: 0.2.1
Summary: A tool for calculating economic optimum nitrogen rates
Home-page: https://github.com/tnigon/eonr
Author: Tyler J. Nigon
Author-email: nigo0024@umn.edu
License: MIT
Platform: UNKNOWN
Classifier: Development Status :: 4 - Beta
Classifier: Intended Audience :: Science/Research
Classifier: Natural Language :: English
Classifier: Operating System :: Microsoft :: Windows
Classifier: Programming Language :: Python :: 3
Requires-Dist: scikits.bootstrap
Requires-Dist: seaborn
Requires-Dist: uncertainties
